control_unit.sv
module control_unit(
    input logic [31:0] instr,
    input logic eq,
    output logic reg_write,
    output logic alu_ctrl,
    output logic alu_src,
    output logic [1:0] imm_src,
    output logic pc_src
);


parameter ADDI_OP = 7'b0010011;
parameter BNE_OP = 7'b1100011;
parameter ADDI_FUNC3 = 3'b000;
parameter BNE_FUNC3 = 3'b001;
parameter alu_add = 3'd0;
parameter alu_subtract =3'd1;

assign alu_src = ((instr[6:0]==ADDI_OP)&&(instr[14:12]==ADDI_FUNC3)) ? 1'b1 : 1'b0;
assign pc_src = ((instr[6:0]==BNE_OP)&&(instr[14:12]==BNE_FUNC3)&&(eq==1'b0)) ? 1'b1 : 1'b0;
assign imm_src = (instr[6:0]==ADDI_OP) ? 2'b00 : 
                 (instr[6:0]==BNE_OP ) ? 2'b10 : 2'b11 ;
assign reg_write = ((instr[6:0]==ADDI_OP)&&(instr[14:12]==ADDI_FUNC3)) ? 1'b1 : 1'b0;
assign alu_ctrl = ((instr[6:0]==ADDI_OP)&&(instr[14:12]==ADDI_FUNC3)) ? 3'd0 : 3'd1;
endmodule

alu.sv
module alu #(
 parameter   DATA_WIDTH = 32
)
(
    input logic [DATA_WIDTH-1:0]       operand1,
    input logic [DATA_WIDTH-1:0]       operand2,
    input logic [2:0]                  alu_ctrl,
    output logic [DATA_WIDTH-1:0]      alu_out,
    output logic                       eq
);

parameter ADDI_OP = 7'b0010011;
parameter BNE_OP = 7'b1100011;
parameter ADDI_FUNC3 = 3'b000;
parameter BNE_FUNC3 = 3'b001;
parameter alu_add = 3'd0;
parameter alu_subtract =3'd1;

assign alu_out = operand1+operand2;//(alu_ctrl==alu_add) ? operand1+operand2 : operand1-operand2;
//assign eq = ((alu_ctrl==alu_subtract)&&(alu_out==0))? 1'b1 : 1'b0;
assign eq = (operand1==operand2);
                 




endmodule

register_file.sv
module register_file #(
    parameter  ADDRESS_WIDTH = 9,
               DATA_WIDTH = 8
)(
    input logic                       clk,
    input logic                       wr_en,
    input logic  [ADDRESS_WIDTH-1:0]  rd_addr1,
    input logic  [ADDRESS_WIDTH-1:0]  rd_addr2,
    input logic  [ADDRESS_WIDTH-1:0]  wr_addr3,
    input logic  [DATA_WIDTH-1:0]     din,
    output logic  [DATA_WIDTH-1:0]     dout1,
    output logic  [DATA_WIDTH-1:0]     dout2,
    output logic  [DATA_WIDTH-1:0]     dout3

);

logic [DATA_WIDTH-1:0] ram_array [2**ADDRESS_WIDTH-1:0];

assign dout1 = (rd_addr1=='h0) ? 32'h0:ram_array[rd_addr1];   

assign dout2 = (rd_addr2=='h0) ? 32'h0:ram_array[rd_addr2];   

assign dout3 = ram_array[11];


always_ff @(posedge clk) begin

    if(wr_en == 1'b1)
    begin
        if(wr_addr3!='h0)
            ram_array[wr_addr3] <= din;
    end
  
end


endmodule

sign_extend.sv
module sign_extend(
    input logic [31:0] instr,
    input logic [1:0]    imm_src,
    output logic [31:0] imm_op
);

//assign imm = (instr[6:0]==7'b0010011) ? instr[31:20] : {instr[31],instr[7],instr[30:25],instr[11:8]};

assign imm_op = (imm_src==2'b00) ? {{20{instr[31]}},instr[31:20]} :
                (imm_src==2'b10) ? {{21{instr[31]}},instr[7],instr[30:25],instr[11:8]} : 32'd0; 


endmodule

instr_mem.sv
module instr_mem #(
    parameter  ADDRESS_WIDTH = 10,
               DATA_WIDTH = 32
)(
    input logic                       clk,
    input logic  [ADDRESS_WIDTH-1:0]  rd_addr,
    output logic  [DATA_WIDTH-1:0]     dout
);


logic [DATA_WIDTH-1:0] ram_array [2**ADDRESS_WIDTH-1:0];

initial begin

    $display("loading ram");
    $readmemh("instruction.mem",ram_array);

end

logic [ADDRESS_WIDTH-1:0] addr;
assign addr = rd_addr>>2;

assign dout = ram_array[addr];



endmodule

pc_reg.sv
module pc_reg(
    input logic clk,
    input logic rst,
    input logic pc_src,
    input logic [31:0] imm,
    output logic [31:0] pc
);

logic [31:0] pc_next;

assign pc_next = pc_src ? (pc+imm) :(pc+4);


always_ff @(posedge clk)
begin
    if(rst)
        pc <= 32'd0;
    else 
        pc <= pc_next;
        
end

endmodule

top.sv
module top(
    input logic clk,
    input logic rst,
    output logic [31:0] result,
    output logic [2:0]  alu_ctrl,
    output logic [31:0] alu_op1,
    output logic [31:0] alu_op2,
    output logic [31:0] imm_op,
    output logic [11:0] imm,
    output logic [31:0] instr,
    output logic pc_src,
    output logic [31:0] pc,
    output logic [1:0]imm_src
    

);


logic [4:0] rd,rs1,rs2;
logic [6:0] op;
logic [2:0] funct3;
//logic [31:0] instr;
//logic [11:0] imm;
//logic [31:0] imm_op;
//logic [31:0] pc;
logic [31:0] alu_out;


logic [31:0] reg_op2;
//logic [31:0] result;
logic eq;
logic reg_write;
//logic alu_ctrl;
logic alu_src;





pc_reg pc_counter(
    .clk(clk),
    .rst(rst),
    .pc_src(pc_src),
    .imm(imm_op),
    .pc(pc)
);

instr_mem  instruction(
    .clk(clk),
    .rd_addr(pc),
    .dout(instr)
);

assign imm = (instr[6:0]==7'b0010011) ? instr[31:20] : {instr[31],instr[7],instr[30:25],instr[11:8]};


sign_extend extension(
    .instr(instr),
    .imm_src(imm_src),
    .imm_op(imm_op)
);



register_file  reg_group(
    .clk(clk),
    .wr_en(reg_write),
    .rd_addr1(instr[19:15]),
    .rd_addr2(instr[24:20]),
    .wr_addr3(instr[11:7]),
    .din(alu_out),
    .dout1(alu_op1),
    .dout2(reg_op2),
    .dout3(result)
);

assign alu_op2 = alu_src ? imm_op : reg_op2;

alu cpu_alu(
    .operand1(alu_op1),
    .operand2(alu_op2),
    .alu_ctrl(alu_ctrl),
    .alu_out(alu_out),
    .eq(eq)
);

control_unit controller(
    .instr(instr),
    .eq(eq),
    .reg_write(reg_write),
    .alu_ctrl(alu_ctrl),
    .alu_src(alu_src),
    .imm_src(imm_src),
    .pc_src(pc_src)
);


endmodule

risc-v.vcd
$version Generated by VerilatedVcd $end
$date Thu Jun 29 19:17:47 2023 $end
$timescale 1ps $end

 $scope module TOP $end
  $var wire  3 & alu_ctrl [2:0] $end
  $var wire 32 ' alu_op1 [31:0] $end
  $var wire 32 ( alu_op2 [31:0] $end
  $var wire  1 # clk $end
  $var wire 12 * imm [11:0] $end
  $var wire 32 ) imm_op [31:0] $end
  $var wire  2 . imm_src [1:0] $end
  $var wire 32 + instr [31:0] $end
  $var wire 32 - pc [31:0] $end
  $var wire  1 , pc_src $end
  $var wire 32 % result [31:0] $end
  $var wire  1 $ rst $end
  $scope module top $end
   $var wire  3 & alu_ctrl [2:0] $end
   $var wire 32 ' alu_op1 [31:0] $end
   $var wire 32 ( alu_op2 [31:0] $end
   $var wire 32 / alu_out [31:0] $end
   $var wire  1 2 alu_src $end
   $var wire  1 # clk $end
   $var wire  1 1 eq $end
   $var wire  3 B funct3 [2:0] $end
   $var wire 12 * imm [11:0] $end
   $var wire 32 ) imm_op [31:0] $end
   $var wire  2 . imm_src [1:0] $end
   $var wire 32 + instr [31:0] $end
   $var wire  7 A op [6:0] $end
   $var wire 32 - pc [31:0] $end
   $var wire  1 , pc_src $end
   $var wire  5 > rd [4:0] $end
   $var wire 32 0 reg_op2 [31:0] $end
   $var wire  1 2 reg_write $end
   $var wire 32 % result [31:0] $end
   $var wire  5 ? rs1 [4:0] $end
   $var wire  5 @ rs2 [4:0] $end
   $var wire  1 $ rst $end
   $scope module controller $end
    $var wire  3 E ADDI_FUNC3 [2:0] $end
    $var wire  7 C ADDI_OP [6:0] $end
    $var wire  3 F BNE_FUNC3 [2:0] $end
    $var wire  7 D BNE_OP [6:0] $end
    $var wire  3 E alu_add [2:0] $end
    $var wire  1 3 alu_ctrl $end
    $var wire  1 2 alu_src $end
    $var wire  3 F alu_subtract [2:0] $end
    $var wire  1 1 eq $end
    $var wire  2 . imm_src [1:0] $end
    $var wire 32 + instr [31:0] $end
    $var wire  1 , pc_src $end
    $var wire  1 2 reg_write $end
   $upscope $end
   $scope module cpu_alu $end
    $var wire  3 E ADDI_FUNC3 [2:0] $end
    $var wire  7 C ADDI_OP [6:0] $end
    $var wire  3 F BNE_FUNC3 [2:0] $end
    $var wire  7 D BNE_OP [6:0] $end
    $var wire 32 G DATA_WIDTH [31:0] $end
    $var wire  3 E alu_add [2:0] $end
    $var wire  3 & alu_ctrl [2:0] $end
    $var wire 32 / alu_out [31:0] $end
    $var wire  3 F alu_subtract [2:0] $end
    $var wire  1 1 eq $end
    $var wire 32 ' operand1 [31:0] $end
    $var wire 32 ( operand2 [31:0] $end
   $upscope $end
   $scope module extension $end
    $var wire 32 ) imm_op [31:0] $end
    $var wire  2 . imm_src [1:0] $end
    $var wire 32 + instr [31:0] $end
   $upscope $end
   $scope module instruction $end
    $var wire 32 H ADDRESS_WIDTH [31:0] $end
    $var wire 32 G DATA_WIDTH [31:0] $end
    $var wire 10 5 addr [9:0] $end
    $var wire  1 # clk $end
    $var wire 32 + dout [31:0] $end
    $var wire 10 4 rd_addr [9:0] $end
   $upscope $end
   $scope module pc_counter $end
    $var wire  1 # clk $end
    $var wire 32 ) imm [31:0] $end
    $var wire 32 - pc [31:0] $end
    $var wire 32 6 pc_next [31:0] $end
    $var wire  1 , pc_src $end
    $var wire  1 $ rst $end
   $upscope $end
   $scope module reg_group $end
    $var wire 32 I ADDRESS_WIDTH [31:0] $end
    $var wire 32 J DATA_WIDTH [31:0] $end
    $var wire  1 # clk $end
    $var wire  8 : din [7:0] $end
    $var wire  8 ; dout1 [7:0] $end
    $var wire  8 < dout2 [7:0] $end
    $var wire  8 = dout3 [7:0] $end
    $var wire  9 7 rd_addr1 [8:0] $end
    $var wire  9 8 rd_addr2 [8:0] $end
    $var wire  9 9 wr_addr3 [8:0] $end
    $var wire  1 2 wr_en $end
   $upscope $end
  $upscope $end
 $upscope $end
$enddefinitions $end


#0
1#
0$
b00000000000000000000000000000000 %
b000 &
b00000000000000000000000000000000 '
b00000000000000000000000000000000 (
b00000000000000000000000000000000 )
b000000000000 *
b00000000000000000000000000000000 +
0,
b00000000000000000000000000000000 -
b00 .
b00000000000000000000000000000000 /
b00000000000000000000000000000000 0
11
02
13
b0000000000 4
b0000000000 5
b00000000000000000000000000000100 6
b000000000 7
b000000000 8
b000000000 9
b00000000 :
b00000000 ;
b00000000 <
b00000000 =
b00000 >
b00000 ?
b00000 @
b0000000 A
b000 B
b0010011 C
b1100011 D
b000 E
b001 F
b00000000000000000000000000100000 G
b00000000000000000000000000001010 H
b00000000000000000000000000001001 I
b00000000000000000000000000001000 J
#1
0#
b00000000000000000000000011111111 (
b00000000000000000000000011111111 )
b000011111111 *
b00001111111100000000001100010011 +
b00000000000000000000000011111111 /
01
12
03
b000011111 8
b000000110 9
b11111111 :
#2
1#
1$
b00000000000000000000000000000000 (
b00000000000000000000000000000000 )
b000000000000 *
b00000000000000000000010100010011 +
b00000000000000000000000000000100 -
b00000000000000000000000000000000 /
11
b0000000100 4
b0000000001 5
b00000000000000000000000000001000 6
b000000000 8
b000001010 9
b00000000 :
#3
0#
#4
1#
b00000000000000000000000011111111 (
b00000000000000000000000011111111 )
b000011111111 *
b00001111111100000000001100010011 +
b00000000000000000000000000000000 -
b00000000000000000000000011111111 /
01
b0000000000 4
b0000000000 5
b00000000000000000000000000000100 6
b000011111 8
b000000110 9
b11111111 :
#5
0#
#6
1#
#7
0#
#8
1#
#9
0#
#10
1#
0$
#11
0#
#12
1#
b00000000000000000000000000000000 (
b00000000000000000000000000000000 )
b000000000000 *
b00000000000000000000010100010011 +
b00000000000000000000000000000100 -
b00000000000000000000000000000000 /
11
b0000000100 4
b0000000001 5
b00000000000000000000000000001000 6
b000000000 8
b000001010 9
b00000000 :
#13
0#
#14
1#
b00000000000000000000010110010011 +
b00000000000000000000000000001000 -
b0000001000 4
b0000000010 5
b00000000000000000000000000001100 6
b000001011 9
#15
0#
#16
1#
b00000000000001011000010100010011 +
b00000000000000000000000000001100 -
b0000001100 4
b0000000011 5
b00000000000000000000000000010000 6
b000001011 7
b000001010 9
#17
0#
#18
1#
b00000000000000000000000000000001 (
b00000000000000000000000000000001 )
b000000000001 *
b00000000000101011000010110010011 +
b00000000000000000000000000010000 -
b00000000000000000000000000000001 /
01
b0000010000 4
b0000000100 5
b00000000000000000000000000010100 6
b000000001 8
b000001011 9
b00000001 :
#19
0#
#20
1#
b00000000000000000000000000000001 %
b001 &
b00000000000000000000000000000001 '
b00000000000000000000000011111111 (
b11111111111111111111111111111100 )
b111111111100 *
b11111110011001011001110011100011 +
1,
b00000000000000000000000000010100 -
b10 .
b00000000000000000000000100000000 /
b00000000000000000000000011111111 0
02
13
b0000010100 4
b0000000101 5
b00000000000000000000000000010000 6
b000000110 8
b000011001 9
b00000000 :
b00000001 ;
b11111111 <
b00000001 =
#21
0#
#22
1#
b000 &
b00000000000000000000000000000001 (
b00000000000000000000000000000001 )
b000000000001 *
b00000000000101011000010110010011 +
0,
b00000000000000000000000000010000 -
b00 .
b00000000000000000000000000000010 /
b00000000000000000000000000000000 0
11
12
03
b0000010000 4
b0000000100 5
b00000000000000000000000000010100 6
b000000001 8
b000001011 9
b00000010 :
b00000000 <
#23
0#
#24
1#
b00000000000000000000000000000010 %
b001 &
b00000000000000000000000000000010 '
b00000000000000000000000011111111 (
b11111111111111111111111111111100 )
b111111111100 *
b11111110011001011001110011100011 +
1,
b00000000000000000000000000010100 -
b10 .
b00000000000000000000000100000001 /
b00000000000000000000000011111111 0
01
02
13
b0000010100 4
b0000000101 5
b00000000000000000000000000010000 6
b000000110 8
b000011001 9
b00000001 :
b00000010 ;
b11111111 <
b00000010 =
#25
0#
#26
1#
b000 &
b00000000000000000000000000000001 (
b00000000000000000000000000000001 )
b000000000001 *
b00000000000101011000010110010011 +
0,
b00000000000000000000000000010000 -
b00 .
b00000000000000000000000000000011 /
b00000000000000000000000000000000 0
12
03
b0000010000 4
b0000000100 5
b00000000000000000000000000010100 6
b000000001 8
b000001011 9
b00000011 :
b00000000 <
#27
0#
#28
1#
b00000000000000000000000000000011 %
b001 &
b00000000000000000000000000000011 '
b00000000000000000000000011111111 (
b11111111111111111111111111111100 )
b111111111100 *
b11111110011001011001110011100011 +
1,
b00000000000000000000000000010100 -
b10 .
b00000000000000000000000100000010 /
b00000000000000000000000011111111 0
02
13
b0000010100 4
b0000000101 5
b00000000000000000000000000010000 6
b000000110 8
b000011001 9
b00000010 :
b00000011 ;
b11111111 <
b00000011 =
#29
0#
#30
1#
b000 &
b00000000000000000000000000000001 (
b00000000000000000000000000000001 )
b000000000001 *
b00000000000101011000010110010011 +
0,
b00000000000000000000000000010000 -
b00 .
b00000000000000000000000000000100 /
b00000000000000000000000000000000 0
12
03
b0000010000 4
b0000000100 5
b00000000000000000000000000010100 6
b000000001 8
b000001011 9
b00000100 :
b00000000 <
#31
0#
#32
1#
b00000000000000000000000000000100 %
b001 &
b00000000000000000000000000000100 '
b00000000000000000000000011111111 (
b11111111111111111111111111111100 )
b111111111100 *
b11111110011001011001110011100011 +
1,
b00000000000000000000000000010100 -
b10 .
b00000000000000000000000100000011 /
b00000000000000000000000011111111 0
02
13
b0000010100 4
b0000000101 5
b00000000000000000000000000010000 6
b000000110 8
b000011001 9
b00000011 :
b00000100 ;
b11111111 <
b00000100 =
#33
0#
#34
1#
b000 &
b00000000000000000000000000000001 (
b00000000000000000000000000000001 )
b000000000001 *
b00000000000101011000010110010011 +
0,
b00000000000000000000000000010000 -
b00 .
b00000000000000000000000000000101 /
b00000000000000000000000000000000 0
12
03
b0000010000 4
b0000000100 5
b00000000000000000000000000010100 6
b000000001 8
b000001011 9
b00000101 :
b00000000 <
#35
0#
#36
1#
b00000000000000000000000000000101 %
b001 &
b00000000000000000000000000000101 '
b00000000000000000000000011111111 (
b11111111111111111111111111111100 )
b111111111100 *
b11111110011001011001110011100011 +
1,
b00000000000000000000000000010100 -
b10 .
b00000000000000000000000100000100 /
b00000000000000000000000011111111 0
02
13
b0000010100 4
b0000000101 5
b00000000000000000000000000010000 6
b000000110 8
b000011001 9
b00000100 :
b00000101 ;
b11111111 <
b00000101 =
#37
0#
#38
1#
b000 &
b00000000000000000000000000000001 (
b00000000000000000000000000000001 )
b000000000001 *
b00000000000101011000010110010011 +
0,
b00000000000000000000000000010000 -
b00 .
b00000000000000000000000000000110 /
b00000000000000000000000000000000 0
12
03
b0000010000 4
b0000000100 5
b00000000000000000000000000010100 6
b000000001 8
b000001011 9
b00000110 :
b00000000 <
#39
0#
#40
1#
b00000000000000000000000000000110 %
b001 &
b00000000000000000000000000000110 '
b00000000000000000000000011111111 (
b11111111111111111111111111111100 )
b111111111100 *
b11111110011001011001110011100011 +
1,
b00000000000000000000000000010100 -
b10 .
b00000000000000000000000100000101 /
b00000000000000000000000011111111 0
02
13
b0000010100 4
b0000000101 5
b00000000000000000000000000010000 6
b000000110 8
b000011001 9
b00000101 :
b00000110 ;
b11111111 <
b00000110 =
#41
0#
#42
1#
b000 &
b00000000000000000000000000000001 (
b00000000000000000000000000000001 )
b000000000001 *
b00000000000101011000010110010011 +
0,
b00000000000000000000000000010000 -
b00 .
b00000000000000000000000000000111 /
b00000000000000000000000000000000 0
12
03
b0000010000 4
b0000000100 5
b00000000000000000000000000010100 6
b000000001 8
b000001011 9
b00000111 :
b00000000 <
#43
0#
#44
1#
b00000000000000000000000000000111 %
b001 &
b00000000000000000000000000000111 '
b00000000000000000000000011111111 (
b11111111111111111111111111111100 )
b111111111100 *
b11111110011001011001110011100011 +
1,
b00000000000000000000000000010100 -
b10 .
b00000000000000000000000100000110 /
b00000000000000000000000011111111 0
02
13
b0000010100 4
b0000000101 5
b00000000000000000000000000010000 6
b000000110 8
b000011001 9
b00000110 :
b00000111 ;
b11111111 <
b00000111 =
#45
0#
#46
1#
b000 &
b00000000000000000000000000000001 (
b00000000000000000000000000000001 )
b000000000001 *
b00000000000101011000010110010011 +
0,
b00000000000000000000000000010000 -
b00 .
b00000000000000000000000000001000 /
b00000000000000000000000000000000 0
12
03
b0000010000 4
b0000000100 5
b00000000000000000000000000010100 6
b000000001 8
b000001011 9
b00001000 :
b00000000 <
#47
0#
#48
1#
b00000000000000000000000000001000 %
b001 &
b00000000000000000000000000001000 '
b00000000000000000000000011111111 (
b11111111111111111111111111111100 )
b111111111100 *
b11111110011001011001110011100011 +
1,
b00000000000000000000000000010100 -
b10 .
b00000000000000000000000100000111 /
b00000000000000000000000011111111 0
02
13
b0000010100 4
b0000000101 5
b00000000000000000000000000010000 6
b000000110 8
b000011001 9
b00000111 :
b00001000 ;
b11111111 <
b00001000 =
#49
0#
#50
1#
b000 &
b00000000000000000000000000000001 (
b00000000000000000000000000000001 )
b000000000001 *
b00000000000101011000010110010011 +
0,
b00000000000000000000000000010000 -
b00 .
b00000000000000000000000000001001 /
b00000000000000000000000000000000 0
12
03
b0000010000 4
b0000000100 5
b00000000000000000000000000010100 6
b000000001 8
b000001011 9
b00001001 :
b00000000 <
#51
0#
#52
1#
b00000000000000000000000000001001 %
b001 &
b00000000000000000000000000001001 '
b00000000000000000000000011111111 (
b11111111111111111111111111111100 )
b111111111100 *
b11111110011001011001110011100011 +
1,
b00000000000000000000000000010100 -
b10 .
b00000000000000000000000100001000 /
b00000000000000000000000011111111 0
02
13
b0000010100 4
b0000000101 5
b00000000000000000000000000010000 6
b000000110 8
b000011001 9
b00001000 :
b00001001 ;
b11111111 <
b00001001 =
#53
0#
#54
1#
b000 &
b00000000000000000000000000000001 (
b00000000000000000000000000000001 )
b000000000001 *
b00000000000101011000010110010011 +
0,
b00000000000000000000000000010000 -
b00 .
b00000000000000000000000000001010 /
b00000000000000000000000000000000 0
12
03
b0000010000 4
b0000000100 5
b00000000000000000000000000010100 6
b000000001 8
b000001011 9
b00001010 :
b00000000 <
#55
0#
#56
1#
b00000000000000000000000000001010 %
b001 &
b00000000000000000000000000001010 '
b00000000000000000000000011111111 (
b11111111111111111111111111111100 )
b111111111100 *
b11111110011001011001110011100011 +
1,
b00000000000000000000000000010100 -
b10 .
b00000000000000000000000100001001 /
b00000000000000000000000011111111 0
02
13
b0000010100 4
b0000000101 5
b00000000000000000000000000010000 6
b000000110 8
b000011001 9
b00001001 :
b00001010 ;
b11111111 <
b00001010 =
#57
0#
#58
1#
b000 &
b00000000000000000000000000000001 (
b00000000000000000000000000000001 )
b000000000001 *
b00000000000101011000010110010011 +
0,
b00000000000000000000000000010000 -
b00 .
b00000000000000000000000000001011 /
b00000000000000000000000000000000 0
12
03
b0000010000 4
b0000000100 5
b00000000000000000000000000010100 6
b000000001 8
b000001011 9
b00001011 :
b00000000 <
#59
0#
#60
1#
b00000000000000000000000000001011 %
b001 &
b00000000000000000000000000001011 '
b00000000000000000000000011111111 (
b11111111111111111111111111111100 )
b111111111100 *
b11111110011001011001110011100011 +
1,
b00000000000000000000000000010100 -
b10 .
b00000000000000000000000100001010 /
b00000000000000000000000011111111 0
02
13
b0000010100 4
b0000000101 5
b00000000000000000000000000010000 6
b000000110 8
b000011001 9
b00001010 :
b00001011 ;
b11111111 <
b00001011 =
#61
0#
#62
1#
b000 &
b00000000000000000000000000000001 (
b00000000000000000000000000000001 )
b000000000001 *
b00000000000101011000010110010011 +
0,
b00000000000000000000000000010000 -
b00 .
b00000000000000000000000000001100 /
b00000000000000000000000000000000 0
12
03
b0000010000 4
b0000000100 5
b00000000000000000000000000010100 6
b000000001 8
b000001011 9
b00001100 :
b00000000 <
#63
0#
#64
1#
b00000000000000000000000000001100 %
b001 &
b00000000000000000000000000001100 '
b00000000000000000000000011111111 (
b11111111111111111111111111111100 )
b111111111100 *
b11111110011001011001110011100011 +
1,
b00000000000000000000000000010100 -
b10 .
b00000000000000000000000100001011 /
b00000000000000000000000011111111 0
02
13
b0000010100 4
b0000000101 5
b00000000000000000000000000010000 6
b000000110 8
b000011001 9
b00001011 :
b00001100 ;
b11111111 <
b00001100 =
#65
0#
#66
1#
b000 &
b00000000000000000000000000000001 (
b00000000000000000000000000000001 )
b000000000001 *
b00000000000101011000010110010011 +
0,
b00000000000000000000000000010000 -
b00 .
b00000000000000000000000000001101 /
b00000000000000000000000000000000 0
12
03
b0000010000 4
b0000000100 5
b00000000000000000000000000010100 6
b000000001 8
b000001011 9
b00001101 :
b00000000 <
#67
0#
#68
1#
b00000000000000000000000000001101 %
b001 &
b00000000000000000000000000001101 '
b00000000000000000000000011111111 (
b11111111111111111111111111111100 )
b111111111100 *
b11111110011001011001110011100011 +
1,
b00000000000000000000000000010100 -
b10 .
b00000000000000000000000100001100 /
b00000000000000000000000011111111 0
02
13
b0000010100 4
b0000000101 5
b00000000000000000000000000010000 6
b000000110 8
b000011001 9
b00001100 :
b00001101 ;
b11111111 <
b00001101 =
#69
0#
#70
1#
b000 &
b00000000000000000000000000000001 (
b00000000000000000000000000000001 )
b000000000001 *
b00000000000101011000010110010011 +
0,
b00000000000000000000000000010000 -
b00 .
b00000000000000000000000000001110 /
b00000000000000000000000000000000 0
12
03
b0000010000 4
b0000000100 5
b00000000000000000000000000010100 6
b000000001 8
b000001011 9
b00001110 :
b00000000 <
#71
0#
#72
1#
b00000000000000000000000000001110 %
b001 &
b00000000000000000000000000001110 '
b00000000000000000000000011111111 (
b11111111111111111111111111111100 )
b111111111100 *
b11111110011001011001110011100011 +
1,
b00000000000000000000000000010100 -
b10 .
b00000000000000000000000100001101 /
b00000000000000000000000011111111 0
02
13
b0000010100 4
b0000000101 5
b00000000000000000000000000010000 6
b000000110 8
b000011001 9
b00001101 :
b00001110 ;
b11111111 <
b00001110 =
#73
0#
#74
1#
b000 &
b00000000000000000000000000000001 (
b00000000000000000000000000000001 )
b000000000001 *
b00000000000101011000010110010011 +
0,
b00000000000000000000000000010000 -
b00 .
b00000000000000000000000000001111 /
b00000000000000000000000000000000 0
12
03
b0000010000 4
b0000000100 5
b00000000000000000000000000010100 6
b000000001 8
b000001011 9
b00001111 :
b00000000 <
#75
0#
#76
1#
b00000000000000000000000000001111 %
b001 &
b00000000000000000000000000001111 '
b00000000000000000000000011111111 (
b11111111111111111111111111111100 )
b111111111100 *
b11111110011001011001110011100011 +
1,
b00000000000000000000000000010100 -
b10 .
b00000000000000000000000100001110 /
b00000000000000000000000011111111 0
02
13
b0000010100 4
b0000000101 5
b00000000000000000000000000010000 6
b000000110 8
b000011001 9
b00001110 :
b00001111 ;
b11111111 <
b00001111 =
#77
0#
#78
1#
b000 &
b00000000000000000000000000000001 (
b00000000000000000000000000000001 )
b000000000001 *
b00000000000101011000010110010011 +
0,
b00000000000000000000000000010000 -
b00 .
b00000000000000000000000000010000 /
b00000000000000000000000000000000 0
12
03
b0000010000 4
b0000000100 5
b00000000000000000000000000010100 6
b000000001 8
b000001011 9
b00010000 :
b00000000 <
#79
0#
#80
1#
b00000000000000000000000000010000 %
b001 &
b00000000000000000000000000010000 '
b00000000000000000000000011111111 (
b11111111111111111111111111111100 )
b111111111100 *
b11111110011001011001110011100011 +
1,
b00000000000000000000000000010100 -
b10 .
b00000000000000000000000100001111 /
b00000000000000000000000011111111 0
02
13
b0000010100 4
b0000000101 5
b00000000000000000000000000010000 6
b000000110 8
b000011001 9
b00001111 :
b00010000 ;
b11111111 <
b00010000 =
#81
0#
#82
1#
b000 &
b00000000000000000000000000000001 (
b00000000000000000000000000000001 )
b000000000001 *
b00000000000101011000010110010011 +
0,
b00000000000000000000000000010000 -
b00 .
b00000000000000000000000000010001 /
b00000000000000000000000000000000 0
12
03
b0000010000 4
b0000000100 5
b00000000000000000000000000010100 6
b000000001 8
b000001011 9
b00010001 :
b00000000 <
#83
0#
#84
1#
b00000000000000000000000000010001 %
b001 &
b00000000000000000000000000010001 '
b00000000000000000000000011111111 (
b11111111111111111111111111111100 )
b111111111100 *
b11111110011001011001110011100011 +
1,
b00000000000000000000000000010100 -
b10 .
b00000000000000000000000100010000 /
b00000000000000000000000011111111 0
02
13
b0000010100 4
b0000000101 5
b00000000000000000000000000010000 6
b000000110 8
b000011001 9
b00010000 :
b00010001 ;
b11111111 <
b00010001 =
#85
0#
#86
1#
b000 &
b00000000000000000000000000000001 (
b00000000000000000000000000000001 )
b000000000001 *
b00000000000101011000010110010011 +
0,
b00000000000000000000000000010000 -
b00 .
b00000000000000000000000000010010 /
b00000000000000000000000000000000 0
12
03
b0000010000 4
b0000000100 5
b00000000000000000000000000010100 6
b000000001 8
b000001011 9
b00010010 :
b00000000 <
#87
0#
#88
1#
b00000000000000000000000000010010 %
b001 &
b00000000000000000000000000010010 '
b00000000000000000000000011111111 (
b11111111111111111111111111111100 )
b111111111100 *
b11111110011001011001110011100011 +
1,
b00000000000000000000000000010100 -
b10 .
b00000000000000000000000100010001 /
b00000000000000000000000011111111 0
02
13
b0000010100 4
b0000000101 5
b00000000000000000000000000010000 6
b000000110 8
b000011001 9
b00010001 :
b00010010 ;
b11111111 <
b00010010 =
#89
0#
#90
1#
b000 &
b00000000000000000000000000000001 (
b00000000000000000000000000000001 )
b000000000001 *
b00000000000101011000010110010011 +
0,
b00000000000000000000000000010000 -
b00 .
b00000000000000000000000000010011 /
b00000000000000000000000000000000 0
12
03
b0000010000 4
b0000000100 5
b00000000000000000000000000010100 6
b000000001 8
b000001011 9
b00010011 :
b00000000 <
#91
0#
#92
1#
b00000000000000000000000000010011 %
b001 &
b00000000000000000000000000010011 '
b00000000000000000000000011111111 (
b11111111111111111111111111111100 )
b111111111100 *
b11111110011001011001110011100011 +
1,
b00000000000000000000000000010100 -
b10 .
b00000000000000000000000100010010 /
b00000000000000000000000011111111 0
02
13
b0000010100 4
b0000000101 5
b00000000000000000000000000010000 6
b000000110 8
b000011001 9
b00010010 :
b00010011 ;
b11111111 <
b00010011 =
#93
0#
#94
1#
b000 &
b00000000000000000000000000000001 (
b00000000000000000000000000000001 )
b000000000001 *
b00000000000101011000010110010011 +
0,
b00000000000000000000000000010000 -
b00 .
b00000000000000000000000000010100 /
b00000000000000000000000000000000 0
12
03
b0000010000 4
b0000000100 5
b00000000000000000000000000010100 6
b000000001 8
b000001011 9
b00010100 :
b00000000 <
#95
0#
#96
1#
b00000000000000000000000000010100 %
b001 &
b00000000000000000000000000010100 '
b00000000000000000000000011111111 (
b11111111111111111111111111111100 )
b111111111100 *
b11111110011001011001110011100011 +
1,
b00000000000000000000000000010100 -
b10 .
b00000000000000000000000100010011 /
b00000000000000000000000011111111 0
02
13
b0000010100 4
b0000000101 5
b00000000000000000000000000010000 6
b000000110 8
b000011001 9
b00010011 :
b00010100 ;
b11111111 <
b00010100 =
#97
0#
#98
1#
b000 &
b00000000000000000000000000000001 (
b00000000000000000000000000000001 )
b000000000001 *
b00000000000101011000010110010011 +
0,
b00000000000000000000000000010000 -
b00 .
b00000000000000000000000000010101 /
b00000000000000000000000000000000 0
12
03
b0000010000 4
b0000000100 5
b00000000000000000000000000010100 6
b000000001 8
b000001011 9
b00010101 :
b00000000 <
#99
0#
#100
1#
b00000000000000000000000000010101 %
b001 &
b00000000000000000000000000010101 '
b00000000000000000000000011111111 (
b11111111111111111111111111111100 )
b111111111100 *
b11111110011001011001110011100011 +
1,
b00000000000000000000000000010100 -
b10 .
b00000000000000000000000100010100 /
b00000000000000000000000011111111 0
02
13
b0000010100 4
b0000000101 5
b00000000000000000000000000010000 6
b000000110 8
b000011001 9
b00010100 :
b00010101 ;
b11111111 <
b00010101 =
#101
0#
#102
1#
b000 &
b00000000000000000000000000000001 (
b00000000000000000000000000000001 )
b000000000001 *
b00000000000101011000010110010011 +
0,
b00000000000000000000000000010000 -
b00 .
b00000000000000000000000000010110 /
b00000000000000000000000000000000 0
12
03
b0000010000 4
b0000000100 5
b00000000000000000000000000010100 6
b000000001 8
b000001011 9
b00010110 :
b00000000 <
#103
0#
